milligram/__init__.py
milligram/api.py
lite_telegram_framework-0.0.6.dist-info/LICENSE
lite_telegram_framework-0.0.6.dist-info/METADATA
lite_telegram_framework-0.0.6.dist-info/WHEEL
lite_telegram_framework-0.0.6.dist-info/top_level.txt
lite_telegram_framework-0.0.6.dist-info/RECORD
